meloetta/__init__.py
meloetta/client.py
meloetta/data.py
meloetta/embeddings.py
meloetta/player.py
meloetta/room.py
meloetta/utils.py
meloetta/vector.py
meloetta/actors/__init__.py
meloetta/actors/base.py
meloetta/actors/types.py
meloetta/frameworks/__init__.py
meloetta/frameworks/max_damage/__init__.py
meloetta/frameworks/max_damage/actor.py
meloetta/frameworks/max_damage/model.py
meloetta/frameworks/mewzero/__init__.py
meloetta/frameworks/mewzero/actor.py
meloetta/frameworks/mewzero/buffer.py
meloetta/frameworks/mewzero/config.py
meloetta/frameworks/mewzero/entropy.py
meloetta/frameworks/mewzero/learner.py
meloetta/frameworks/mewzero/train.py
meloetta/frameworks/mewzero/tree.py
meloetta/frameworks/mewzero/utils.py
meloetta/frameworks/mewzero/model/__init__.py
meloetta/frameworks/mewzero/model/config.py
meloetta/frameworks/mewzero/model/core.py
meloetta/frameworks/mewzero/model/encoder.py
meloetta/frameworks/mewzero/model/interfaces.py
meloetta/frameworks/mewzero/model/main.py
meloetta/frameworks/mewzero/model/policy.py
meloetta/frameworks/mewzero/model/utils.py
meloetta/frameworks/mewzero/model/value.py
meloetta/frameworks/mewzero/model/encoders/__init__.py
meloetta/frameworks/mewzero/model/encoders/private_encoder.py
meloetta/frameworks/mewzero/model/encoders/private_spatial.py
meloetta/frameworks/mewzero/model/encoders/public_encoder.py
meloetta/frameworks/mewzero/model/encoders/public_spatial.py
meloetta/frameworks/mewzero/model/encoders/scalar_encoder.py
meloetta/frameworks/mewzero/model/encoders/weather_encoder.py
meloetta/frameworks/mewzero/model/heads/__init__.py
meloetta/frameworks/mewzero/model/heads/action_type_head.py
meloetta/frameworks/mewzero/model/heads/flag_head.py
meloetta/frameworks/mewzero/model/heads/max_move_head.py
meloetta/frameworks/mewzero/model/heads/move_head.py
meloetta/frameworks/mewzero/model/heads/switch_head.py
meloetta/frameworks/nash_ketchum/__init__.py
meloetta/frameworks/nash_ketchum/actor.py
meloetta-1.1.0.dist-info/LICENSE
meloetta-1.1.0.dist-info/METADATA
meloetta-1.1.0.dist-info/WHEEL
meloetta-1.1.0.dist-info/top_level.txt
meloetta-1.1.0.dist-info/RECORD
