Metadata-Version: 2.1
Name: meloetta
Version: 1.1.0
Home-page: https://github.com/spktrm/meloetta
Author: Joseph Twin
Author-email: joseph.twin14@gmail.com
License-File: LICENSE
Requires-Dist: beautifulsoup4 (==4.12.2)
Requires-Dist: jax (==0.3.14)
Requires-Dist: detoxify (==0.5.1)
Requires-Dist: pandas (==1.3.5)
Requires-Dist: numpy (==1.21.5)
Requires-Dist: py-mini-racer (==0.6.0)
Requires-Dist: plotly (==5.11.0)
Requires-Dist: scikit-learn (==1.2.2)
Requires-Dist: requests (==2.26.0)
Requires-Dist: torch (==1.13.0)
Requires-Dist: setuptools (==58.0.0)
Requires-Dist: tqdm (==4.64.1)
Requires-Dist: websockets (==10.1)
Provides-Extra: core_tests
Requires-Dist: transformers[torch] (==4.18.0) ; extra == 'core_tests'
Requires-Dist: sentence-transformers (==2.2.0) ; extra == 'core_tests'
Requires-Dist: huggingface-hub (==0.4.0) ; extra == 'core_tests'
